README.rst
setup.cfg
setup.py
bat_min/__init__.py
bat_min/bro_log_reader.py
bat_min/bro_multi_log_reader.py
bat_min/data_generator.py
bat_min/dataframe_cache.py
bat_min/dataframe_stats.py
bat_min/dataframe_to_matrix.py
bat_min/dataframe_to_parquet.py
bat_min/live_simulator.py
bat_min/log_to_dataframe.py
bat_min/log_to_parquet.py
bat_min.egg-info/PKG-INFO
bat_min.egg-info/SOURCES.txt
bat_min.egg-info/dependency_links.txt
bat_min.egg-info/requires.txt
bat_min.egg-info/top_level.txt
bat_min/utils/__init__.py
bat_min/utils/cache.py
bat_min/utils/compat.py
bat_min/utils/dir_watcher.py
bat_min/utils/dummy_encoder.py
bat_min/utils/file_tailer.py
bat_min/utils/file_utils.py
bat_min/utils/net_utils.py
bat_min/utils/ngrams.py
bat_min/utils/plot_utils.py
bat_min/utils/reverse_dns.py
bat_min/utils/signal_utils.py
bat_min/utils/vt_query.py