Metadata-Version: 1.1
Name: bat-min
Version: 0.3.2
Summary: Bro Analysis Tools
Home-page: https://github.com/kitware/bat
Author: Brian Wylie
Author-email: brian.wylie@kitware.com
License: Apache
Keywords: Bro,Python,Networking,Security,Scikit-Learn,Spark,Kafka,Parquet
Platform: UNKNOWN
Classifier: Development Status :: 2 - Pre-Alpha
Classifier: Intended Audience :: Developers
Classifier: License :: OSI Approved :: Apache Software License
Classifier: Natural Language :: English
Classifier: Programming Language :: Python :: 2.7
Classifier: Programming Language :: Python :: 3.5
Classifier: Programming Language :: Python :: 3.6
Classifier: Programming Language :: Python :: Implementation :: CPython
Classifier: Programming Language :: Python :: Implementation :: PyPy
